logya/__about__.py
logya/__init__.py
logya/commands.py
logya/content.py
logya/core.py
logya/docparser.py
logya/encoder.py
logya/main.py
logya/server.py
logya/template.py
logya/util.py
logya/sites/base/.gitignore
logya/sites/base/README.md
logya/sites/base/site.yaml
logya/sites/base/content/404.md
logya/sites/base/content/about.md
logya/sites/base/content/contact.html
logya/sites/base/content/index.md
logya/sites/base/content/rss.xml
logya/sites/base/content/sitemap.xml
logya/sites/base/content/using-tags.md
logya/sites/base/static/.htaccess
logya/sites/base/static/.nojekyll
logya/sites/base/static/favicon.ico
logya/sites/base/static/robots.txt
logya/sites/base/static/style.css
logya/sites/base/static/img/logya-small.png
logya/sites/base/templates/base.html
logya/sites/base/templates/index.html
logya/sites/base/templates/macros.html
logya/sites/base/templates/page.html
logya/sites/base/templates/post.html
logya/sites/base/templates/rss2.xml
logya/sites/base/templates/sitemap.xml
logya/sites/docs/.gitignore
logya/sites/docs/README.md
logya/sites/docs/site.yaml
logya/sites/docs/content/404.md
logya/sites/docs/content/changes.md
logya/sites/docs/content/configuration.md
logya/sites/docs/content/create.md
logya/sites/docs/content/documentstructure.md
logya/sites/docs/content/gettingstarted.md
logya/sites/docs/content/i18n.md
logya/sites/docs/content/index.html
logya/sites/docs/content/installation.md
logya/sites/docs/content/recipes.md
logya/sites/docs/content/rss.xml
logya/sites/docs/content/sitemap.xml
logya/sites/docs/content/templates.md
logya/sites/docs/static/favicon.ico
logya/sites/docs/static/robots.txt
logya/sites/docs/static/style.css
logya/sites/docs/static/img/logya-small.png
logya/sites/docs/static/img/small.gif
logya/sites/docs/templates/base.html
logya/sites/docs/templates/index.html
logya/sites/docs/templates/macros.html
logya/sites/docs/templates/page.html
logya/sites/docs/templates/post.html
logya/sites/docs/templates/rss2.xml
logya-6.0.0.dist-info/METADATA
logya-6.0.0.dist-info/WHEEL
logya-6.0.0.dist-info/entry_points.txt
logya-6.0.0.dist-info/licenses/LICENSE
logya-6.0.0.dist-info/RECORD
